{
 "accept_payment": 0,
 "allow_comments": 0,
 "allow_delete": 0,
 "allow_edit": 0,
 "allow_incomplete": 0,
 "allow_multiple": 0,
 "allow_print": 0,
 "amount": 0.0,
 "amount_based_on_field": 0,
 "anonymous": 0,
 "apply_document_permissions": 0,
 "banner_image": "/files/Asset 7.png",
 "breadcrumbs": "[{\"label\": _(\"Jobs\"), \"route\":\"jobs\"}]",
 "button_label": "Save",
 "client_script": "\tfrappe.web_form.validate  = () => {\r\n\t\tlet data = frappe.web_form.get_values();\r\n\t\tconsole.log(data)\r\n\t\tfrappe.web_form.on('customer_family_detail', (field, value) => {\r\n\t\t\tconsole.log(field, value)\r\n\t\t});\r\n\t}",
 "creation": "2023-09-21 12:26:07.548083",
 "currency": "SAR",
 "custom_css": ".web-form-header {\r\n    margin-bottom: 2rem;\r\n    border: 1px solid var(--blue-200) !important;\r\n    border-radius: var(--border-radius);\r\n    background-color: var(--blue-50) !important;\r\n}\r\n\r\n.web-form-head {\r\n    border: none !important;\r\n    padding-bottom: 2rem !important;\r\n}\r\n\r\n.web-form {\r\n    border: 1px solid var(--dark-border-color) !important;\r\n    border-radius: var(--border-radius);\r\n    padding-top: 2rem !important;\r\n}\r\n.navbar .container {\r\n        background: linear-gradient(to bottom right, #6f17de, #56388c);\r\n\r\n}\r\n.navbar .navbar-collapse {\r\n    background-color:transparent;\r\n    z-index: 1;\r\n    padding-left: 5px;\r\n}\r\n\r\n.navbar-light .navbar-nav .nav-link {\r\n    color: white;\r\n    background-color: #7a09ff;\r\n    color: white;\r\n    /* font-weight: bold; */\r\n    /* display: flex; */\r\n    /* justify-content: center; */\r\n    /* align-items: center; */\r\n    /* padding: 8px 16px; */\r\n    border-radius: 100px;\r\n    /* font-size: 20px; */\r\n    /* width: 110px; */\r\n    /* height: 25px; */\r\n    -webkit-border-radius: 100px;\r\n    -moz-border-radius: 100px;\r\n    -ms-border-radius: 100px\r\n}\r\n.web-form-header {\r\n    background: linear-gradient(to bottom right, #6f17de, #56388c);\r\n}\r\n.web-form-head{\r\n    color:white;\r\n}\r\n.web-form-title ellipsis {\r\n    color:white;\r\n}\r\nh1 {\r\n    color:white;\r\n}\r\np{\r\n    color:#f19a33!important;\r\n}\r\n\r\n.left-images {\r\n    display: flex;\r\n    flex-direction: column;\r\n}\r\n\r\n.left-images img {\r\n    width: 120px;\r\n    height: auto;\r\n    margin-bottom: 10px;\r\n}",
 "doc_type": "Customer",
 "docstatus": 0,
 "doctype": "Web Form",
 "idx": 0,
 "introduction_text": "<div class=\"ql-editor read-mode\"><p>Customer Details</p></div>",
 "is_standard": 1,
 "list_columns": [],
 "login_required": 0,
 "max_attachment_size": 10,
 "modified": "2023-09-21 18:07:53.757460",
 "modified_by": "Administrator",
 "module": "Ecs Vim",
 "name": "customer-details",
 "owner": "Administrator",
 "payment_button_label": "Buy Now",
 "published": 1,
 "route": "customer-details",
 "show_attachments": 0,
 "show_list": 0,
 "show_sidebar": 0,
 "title": "Customer Details",
 "web_form_fields": [
  {
   "allow_read_on_all_link_options": 0,
   "fieldname": "first_name",
   "fieldtype": "Data",
   "hidden": 0,
   "label": "First Name",
   "max_length": 0,
   "max_value": 0,
   "read_only": 0,
   "reqd": 1,
   "show_in_filter": 0
  },
  {
   "allow_read_on_all_link_options": 0,
   "fieldname": "last_name",
   "fieldtype": "Data",
   "hidden": 0,
   "label": "Last Name",
   "max_length": 0,
   "max_value": 0,
   "read_only": 0,
   "reqd": 1,
   "show_in_filter": 0
  },
  {
   "allow_read_on_all_link_options": 0,
   "fieldname": "middle_name",
   "fieldtype": "Data",
   "hidden": 0,
   "label": "Middle Name",
   "max_length": 0,
   "max_value": 0,
   "read_only": 0,
   "reqd": 0,
   "show_in_filter": 0
  },
  {
   "allow_read_on_all_link_options": 0,
   "fieldname": "territory",
   "fieldtype": "Link",
   "hidden": 0,
   "label": "Territory",
   "max_length": 0,
   "max_value": 0,
   "options": "Territory",
   "read_only": 0,
   "reqd": 1,
   "show_in_filter": 0
  },
  {
   "allow_read_on_all_link_options": 0,
   "fieldname": "favourite_venue",
   "fieldtype": "Data",
   "hidden": 0,
   "label": "Favourite Venue",
   "max_length": 0,
   "max_value": 0,
   "read_only": 0,
   "reqd": 0,
   "show_in_filter": 0
  },
  {
   "allow_read_on_all_link_options": 0,
   "fieldname": "industry",
   "fieldtype": "Link",
   "hidden": 0,
   "label": "Industry",
   "max_length": 0,
   "max_value": 0,
   "options": "Industry Type",
   "read_only": 0,
   "reqd": 0,
   "show_in_filter": 0
  },
  {
   "allow_read_on_all_link_options": 0,
   "fieldname": "nationality",
   "fieldtype": "Link",
   "hidden": 0,
   "label": "Nationality",
   "max_length": 0,
   "max_value": 0,
   "options": "Country",
   "read_only": 0,
   "reqd": 0,
   "show_in_filter": 0
  },
  {
   "allow_read_on_all_link_options": 0,
   "default": "",
   "fieldname": "city",
   "fieldtype": "Link",
   "hidden": 0,
   "label": "City",
   "max_length": 0,
   "max_value": 0,
   "options": "City",
   "read_only": 0,
   "reqd": 0,
   "show_in_filter": 0
  },
  {
   "allow_read_on_all_link_options": 0,
   "fieldname": "district",
   "fieldtype": "Data",
   "hidden": 0,
   "label": "District",
   "max_length": 0,
   "max_value": 0,
   "read_only": 1,
   "reqd": 0,
   "show_in_filter": 0
  },
  {
   "allow_read_on_all_link_options": 0,
   "default": "",
   "fieldname": "branch",
   "fieldtype": "Link",
   "hidden": 0,
   "label": "Branch",
   "max_length": 0,
   "max_value": 0,
   "options": "Dimension Branch",
   "read_only": 0,
   "reqd": 0,
   "show_in_filter": 0
  },
  {
   "allow_read_on_all_link_options": 0,
   "fieldname": "preferred_communication",
   "fieldtype": "Link",
   "hidden": 0,
   "label": "Preferred Communication",
   "max_length": 0,
   "max_value": 0,
   "options": "Preferred Communication",
   "read_only": 0,
   "reqd": 0,
   "show_in_filter": 0
  },
  {
   "allow_read_on_all_link_options": 0,
   "fieldname": "customer_family_detail",
   "fieldtype": "Table",
   "hidden": 0,
   "label": "Customer Family Detail",
   "max_length": 0,
   "max_value": 0,
   "options": "Customer Family Detail",
   "read_only": 0,
   "reqd": 0,
   "show_in_filter": 0
  },
  {
   "allow_read_on_all_link_options": 0,
   "fieldname": "language",
   "fieldtype": "Link",
   "hidden": 0,
   "label": "Print Language",
   "max_length": 0,
   "max_value": 0,
   "options": "Language",
   "read_only": 0,
   "reqd": 0,
   "show_in_filter": 0
  },
  {
   "allow_read_on_all_link_options": 0,
   "fieldname": "customer_details",
   "fieldtype": "Text",
   "hidden": 0,
   "label": "Customer Details",
   "max_length": 0,
   "max_value": 0,
   "read_only": 0,
   "reqd": 0,
   "show_in_filter": 0
  },
  {
   "allow_read_on_all_link_options": 0,
   "fieldname": "customer_primary_contact",
   "fieldtype": "Link",
   "hidden": 0,
   "label": "Customer Primary Contact",
   "max_length": 0,
   "max_value": 0,
   "options": "Contact",
   "read_only": 0,
   "reqd": 0,
   "show_in_filter": 0
  },
  {
   "allow_read_on_all_link_options": 0,
   "fieldname": "country_code",
   "fieldtype": "Data",
   "hidden": 0,
   "label": "Country Code",
   "max_length": 0,
   "max_value": 0,
   "read_only": 1,
   "reqd": 0,
   "show_in_filter": 0
  },
  {
   "allow_read_on_all_link_options": 0,
   "depends_on": "",
   "fieldname": "temporary_mobile_no",
   "fieldtype": "Data",
   "hidden": 0,
   "label": "Mobile No(Internal Use)",
   "max_length": 0,
   "max_value": 0,
   "read_only": 0,
   "reqd": 0,
   "show_in_filter": 0
  },
  {
   "allow_read_on_all_link_options": 0,
   "fieldname": "eid",
   "fieldtype": "Data",
   "hidden": 0,
   "label": "eid",
   "max_length": 0,
   "max_value": 0,
   "read_only": 0,
   "reqd": 0,
   "show_in_filter": 0
  },
  {
   "allow_read_on_all_link_options": 0,
   "fieldname": "customer_primary_address",
   "fieldtype": "Link",
   "hidden": 0,
   "label": "Customer Primary Address",
   "max_length": 0,
   "max_value": 0,
   "options": "Address",
   "read_only": 0,
   "reqd": 0,
   "show_in_filter": 0
  },
  {
   "allow_read_on_all_link_options": 0,
   "fieldname": "primary_address",
   "fieldtype": "Text",
   "hidden": 0,
   "label": "Primary Address",
   "max_length": 0,
   "max_value": 0,
   "read_only": 1,
   "reqd": 0,
   "show_in_filter": 0
  },
  {
   "allow_read_on_all_link_options": 0,
   "fieldname": "tax_id",
   "fieldtype": "Data",
   "hidden": 0,
   "label": "Tax ID",
   "max_length": 0,
   "max_value": 0,
   "read_only": 0,
   "reqd": 0,
   "show_in_filter": 0
  },
  {
   "allow_read_on_all_link_options": 0,
   "fieldname": "loyalty_program",
   "fieldtype": "Link",
   "hidden": 0,
   "label": "Loyalty Program",
   "max_length": 0,
   "max_value": 0,
   "options": "Loyalty Program",
   "read_only": 0,
   "reqd": 0,
   "show_in_filter": 0
  },
  {
   "allow_read_on_all_link_options": 0,
   "fieldname": "loyalty_program_tier",
   "fieldtype": "Data",
   "hidden": 0,
   "label": "Loyalty Program Tier",
   "max_length": 0,
   "max_value": 0,
   "read_only": 1,
   "reqd": 0,
   "show_in_filter": 0
  },
  {
   "allow_read_on_all_link_options": 0,
   "fieldname": "customer_name",
   "fieldtype": "Data",
   "hidden": 0,
   "label": "Customer Name",
   "max_length": 0,
   "max_value": 0,
   "read_only": 0,
   "reqd": 0,
   "show_in_filter": 0
  },
  {
   "allow_read_on_all_link_options": 0,
   "fieldname": "customer_primary_contact",
   "fieldtype": "Data",
   "hidden": 0,
   "label": "Customer Primary Contact",
   "max_length": 0,
   "max_value": 0,
   "options": "",
   "read_only": 0,
   "reqd": 0,
   "show_in_filter": 0
  },
  {
   "allow_read_on_all_link_options": 0,
   "fieldname": "first_name",
   "fieldtype": "Data",
   "hidden": 0,
   "label": "First Name",
   "max_length": 0,
   "max_value": 0,
   "read_only": 0,
   "reqd": 0,
   "show_in_filter": 0
  }
 ]
}