{
 "custom_fields": [
  {
   "_assign": null,
   "_comments": null,
   "_liked_by": null,
   "_user_tags": null,
   "allow_in_quick_entry": 0,
   "allow_on_submit": 1,
   "bold": 0,
   "collapsible": 0,
   "collapsible_depends_on": null,
   "columns": 0,
   "creation": "2022-11-17 14:44:44.788982",
   "default": null,
   "depends_on": null,
   "description": null,
   "docstatus": 0,
   "dt": "Sales Invoice Item",
   "fetch_from": "item_code.gst_hsn_code",
   "fetch_if_empty": 1,
   "fieldname": "gst_hsn_code",
   "fieldtype": "Data",
   "hidden": 0,
   "hide_border": 0,
   "hide_days": 0,
   "hide_seconds": 0,
   "idx": 106,
   "ignore_user_permissions": 0,
   "ignore_xss_filter": 0,
   "in_global_search": 0,
   "in_list_view": 0,
   "in_preview": 0,
   "in_standard_filter": 0,
   "insert_after": "page_break",
   "is_system_generated": 1,
   "is_virtual": 0,
   "label": "HSN/SAC",
   "length": 0,
   "mandatory_depends_on": null,
   "modified": "2021-12-25 12:57:56.661372",
   "modified_by": "Administrator",
   "module": null,
   "name": "Sales Invoice Item-gst_hsn_code",
   "no_copy": 0,
   "non_negative": 0,
   "options": null,
   "owner": "Administrator",
   "parent": null,
   "parentfield": null,
   "parenttype": null,
   "permlevel": 0,
   "precision": "",
   "print_hide": 1,
   "print_hide_if_no_value": 0,
   "print_width": null,
   "read_only": 0,
   "read_only_depends_on": null,
   "report_hide": 0,
   "reqd": 0,
   "search_index": 0,
   "sort_options": 0,
   "translatable": 1,
   "unique": 0,
   "width": null
  },
  {
   "_assign": null,
   "_comments": null,
   "_liked_by": null,
   "_user_tags": null,
   "allow_in_quick_entry": 0,
   "allow_on_submit": 0,
   "bold": 0,
   "collapsible": 0,
   "collapsible_depends_on": null,
   "columns": 0,
   "creation": "2022-11-17 14:44:45.575349",
   "default": null,
   "depends_on": null,
   "description": null,
   "docstatus": 0,
   "dt": "Sales Invoice Item",
   "fetch_from": "item_code.is_nil_exempt",
   "fetch_if_empty": 0,
   "fieldname": "is_nil_exempt",
   "fieldtype": "Check",
   "hidden": 0,
   "hide_border": 0,
   "hide_days": 0,
   "hide_seconds": 0,
   "idx": 107,
   "ignore_user_permissions": 0,
   "ignore_xss_filter": 0,
   "in_global_search": 0,
   "in_list_view": 0,
   "in_preview": 0,
   "in_standard_filter": 0,
   "insert_after": "gst_hsn_code",
   "is_system_generated": 1,
   "is_virtual": 0,
   "label": "Is Nil Rated or Exempted",
   "length": 0,
   "mandatory_depends_on": null,
   "modified": "2021-12-25 12:57:56.860717",
   "modified_by": "Administrator",
   "module": null,
   "name": "Sales Invoice Item-is_nil_exempt",
   "no_copy": 0,
   "non_negative": 0,
   "options": null,
   "owner": "Administrator",
   "parent": null,
   "parentfield": null,
   "parenttype": null,
   "permlevel": 0,
   "precision": "",
   "print_hide": 1,
   "print_hide_if_no_value": 0,
   "print_width": null,
   "read_only": 0,
   "read_only_depends_on": null,
   "report_hide": 0,
   "reqd": 0,
   "search_index": 0,
   "sort_options": 0,
   "translatable": 0,
   "unique": 0,
   "width": null
  },
  {
   "_assign": null,
   "_comments": null,
   "_liked_by": null,
   "_user_tags": null,
   "allow_in_quick_entry": 0,
   "allow_on_submit": 0,
   "bold": 0,
   "collapsible": 0,
   "collapsible_depends_on": null,
   "columns": 0,
   "creation": "2022-11-17 14:44:46.332463",
   "default": null,
   "depends_on": null,
   "description": null,
   "docstatus": 0,
   "dt": "Sales Invoice Item",
   "fetch_from": "item_code.is_non_gst",
   "fetch_if_empty": 0,
   "fieldname": "is_non_gst",
   "fieldtype": "Check",
   "hidden": 0,
   "hide_border": 0,
   "hide_days": 0,
   "hide_seconds": 0,
   "idx": 108,
   "ignore_user_permissions": 0,
   "ignore_xss_filter": 0,
   "in_global_search": 0,
   "in_list_view": 0,
   "in_preview": 0,
   "in_standard_filter": 0,
   "insert_after": "is_nil_exempt",
   "is_system_generated": 1,
   "is_virtual": 0,
   "label": "Is Non GST",
   "length": 0,
   "mandatory_depends_on": null,
   "modified": "2021-12-25 12:57:57.064473",
   "modified_by": "Administrator",
   "module": null,
   "name": "Sales Invoice Item-is_non_gst",
   "no_copy": 0,
   "non_negative": 0,
   "options": null,
   "owner": "Administrator",
   "parent": null,
   "parentfield": null,
   "parenttype": null,
   "permlevel": 0,
   "precision": "",
   "print_hide": 1,
   "print_hide_if_no_value": 0,
   "print_width": null,
   "read_only": 0,
   "read_only_depends_on": null,
   "report_hide": 0,
   "reqd": 0,
   "search_index": 0,
   "sort_options": 0,
   "translatable": 0,
   "unique": 0,
   "width": null
  },
  {
   "_assign": null,
   "_comments": null,
   "_liked_by": null,
   "_user_tags": null,
   "allow_in_quick_entry": 0,
   "allow_on_submit": 0,
   "bold": 0,
   "collapsible": 0,
   "collapsible_depends_on": null,
   "columns": 0,
   "creation": "2022-11-17 14:44:24.106758",
   "default": null,
   "depends_on": null,
   "description": null,
   "docstatus": 0,
   "dt": "Sales Invoice Item",
   "fetch_from": null,
   "fetch_if_empty": 0,
   "fieldname": "taxable_value",
   "fieldtype": "Currency",
   "hidden": 1,
   "hide_border": 0,
   "hide_days": 0,
   "hide_seconds": 0,
   "idx": 53,
   "ignore_user_permissions": 0,
   "ignore_xss_filter": 0,
   "in_global_search": 0,
   "in_list_view": 0,
   "in_preview": 0,
   "in_standard_filter": 0,
   "insert_after": "base_net_amount",
   "is_system_generated": 1,
   "is_virtual": 0,
   "label": "Taxable Value",
   "length": 0,
   "mandatory_depends_on": null,
   "modified": "2021-12-25 12:57:57.270010",
   "modified_by": "Administrator",
   "module": null,
   "name": "Sales Invoice Item-taxable_value",
   "no_copy": 0,
   "non_negative": 0,
   "options": "Company:company:default_currency",
   "owner": "Administrator",
   "parent": null,
   "parentfield": null,
   "parenttype": null,
   "permlevel": 0,
   "precision": "",
   "print_hide": 1,
   "print_hide_if_no_value": 0,
   "print_width": null,
   "read_only": 0,
   "read_only_depends_on": null,
   "report_hide": 0,
   "reqd": 0,
   "search_index": 0,
   "sort_options": 0,
   "translatable": 0,
   "unique": 0,
   "width": null
  },
  {
   "_assign": null,
   "_comments": null,
   "_liked_by": null,
   "_user_tags": null,
   "allow_in_quick_entry": 0,
   "allow_on_submit": 1,
   "bold": 0,
   "collapsible": 0,
   "collapsible_depends_on": null,
   "columns": 0,
   "creation": "2023-10-06 01:00:32.869517",
   "default": null,
   "depends_on": null,
   "description": null,
   "docstatus": 0,
   "dt": "Sales Invoice Item",
   "fetch_from": "item_code.tax_code",
   "fetch_if_empty": 0,
   "fieldname": "tax_code",
   "fieldtype": "Read Only",
   "hidden": 0,
   "hide_border": 0,
   "hide_days": 0,
   "hide_seconds": 0,
   "idx": 9,
   "ignore_user_permissions": 0,
   "ignore_xss_filter": 0,
   "in_global_search": 0,
   "in_list_view": 0,
   "in_preview": 0,
   "in_standard_filter": 0,
   "insert_after": "description",
   "is_system_generated": 1,
   "is_virtual": 0,
   "label": "Tax Code",
   "length": 0,
   "mandatory_depends_on": null,
   "modified": "2021-12-25 13:09:21.988877",
   "modified_by": "Administrator",
   "module": null,
   "name": "Sales Invoice Item-tax_code",
   "no_copy": 0,
   "non_negative": 0,
   "options": null,
   "owner": null,
   "parent": null,
   "parentfield": null,
   "parenttype": null,
   "permlevel": 0,
   "precision": "",
   "print_hide": 1,
   "print_hide_if_no_value": 0,
   "print_width": null,
   "read_only": 0,
   "read_only_depends_on": null,
   "report_hide": 0,
   "reqd": 0,
   "search_index": 0,
   "sort_options": 0,
   "translatable": 0,
   "unique": 0,
   "width": null
  },
  {
   "_assign": null,
   "_comments": null,
   "_liked_by": null,
   "_user_tags": null,
   "allow_in_quick_entry": 0,
   "allow_on_submit": 0,
   "bold": 0,
   "collapsible": 0,
   "collapsible_depends_on": null,
   "columns": 0,
   "creation": "2023-10-06 01:00:45.883713",
   "default": null,
   "depends_on": null,
   "description": null,
   "docstatus": 0,
   "dt": "Sales Invoice Item",
   "fetch_from": null,
   "fetch_if_empty": 0,
   "fieldname": "tax_rate",
   "fieldtype": "Float",
   "hidden": 1,
   "hide_border": 0,
   "hide_days": 0,
   "hide_seconds": 0,
   "idx": 10,
   "ignore_user_permissions": 0,
   "ignore_xss_filter": 0,
   "in_global_search": 0,
   "in_list_view": 0,
   "in_preview": 0,
   "in_standard_filter": 0,
   "insert_after": "tax_code",
   "is_system_generated": 1,
   "is_virtual": 0,
   "label": "Tax Rate",
   "length": 0,
   "mandatory_depends_on": null,
   "modified": "2021-12-25 13:09:22.147591",
   "modified_by": "Administrator",
   "module": null,
   "name": "Sales Invoice Item-tax_rate",
   "no_copy": 0,
   "non_negative": 0,
   "options": null,
   "owner": null,
   "parent": null,
   "parentfield": null,
   "parenttype": null,
   "permlevel": 0,
   "precision": "",
   "print_hide": 1,
   "print_hide_if_no_value": 0,
   "print_width": null,
   "read_only": 1,
   "read_only_depends_on": null,
   "report_hide": 0,
   "reqd": 0,
   "search_index": 0,
   "sort_options": 0,
   "translatable": 0,
   "unique": 0,
   "width": null
  },
  {
   "_assign": null,
   "_comments": null,
   "_liked_by": null,
   "_user_tags": null,
   "allow_in_quick_entry": 0,
   "allow_on_submit": 0,
   "bold": 0,
   "collapsible": 0,
   "collapsible_depends_on": null,
   "columns": 0,
   "creation": "2023-10-06 01:00:56.134498",
   "default": null,
   "depends_on": null,
   "description": null,
   "docstatus": 0,
   "dt": "Sales Invoice Item",
   "fetch_from": null,
   "fetch_if_empty": 0,
   "fieldname": "tax_amount",
   "fieldtype": "Currency",
   "hidden": 1,
   "hide_border": 0,
   "hide_days": 0,
   "hide_seconds": 0,
   "idx": 11,
   "ignore_user_permissions": 0,
   "ignore_xss_filter": 0,
   "in_global_search": 0,
   "in_list_view": 0,
   "in_preview": 0,
   "in_standard_filter": 0,
   "insert_after": "tax_rate",
   "is_system_generated": 1,
   "is_virtual": 0,
   "label": "Tax Amount",
   "length": 0,
   "mandatory_depends_on": null,
   "modified": "2021-12-25 13:09:22.303213",
   "modified_by": "Administrator",
   "module": null,
   "name": "Sales Invoice Item-tax_amount",
   "no_copy": 0,
   "non_negative": 0,
   "options": "currency",
   "owner": null,
   "parent": null,
   "parentfield": null,
   "parenttype": null,
   "permlevel": 0,
   "precision": "",
   "print_hide": 1,
   "print_hide_if_no_value": 0,
   "print_width": null,
   "read_only": 1,
   "read_only_depends_on": null,
   "report_hide": 0,
   "reqd": 0,
   "search_index": 0,
   "sort_options": 0,
   "translatable": 0,
   "unique": 0,
   "width": null
  },
  {
   "_assign": null,
   "_comments": null,
   "_liked_by": null,
   "_user_tags": null,
   "allow_in_quick_entry": 0,
   "allow_on_submit": 0,
   "bold": 0,
   "collapsible": 0,
   "collapsible_depends_on": null,
   "columns": 0,
   "creation": "2022-11-17 14:43:24.564333",
   "default": null,
   "depends_on": null,
   "description": null,
   "docstatus": 0,
   "dt": "Sales Invoice Item",
   "fetch_from": null,
   "fetch_if_empty": 0,
   "fieldname": "total_amount",
   "fieldtype": "Currency",
   "hidden": 1,
   "hide_border": 0,
   "hide_days": 0,
   "hide_seconds": 0,
   "idx": 11,
   "ignore_user_permissions": 0,
   "ignore_xss_filter": 0,
   "in_global_search": 0,
   "in_list_view": 0,
   "in_preview": 0,
   "in_standard_filter": 0,
   "insert_after": "tax_amount",
   "is_system_generated": 1,
   "is_virtual": 0,
   "label": "Total Amount",
   "length": 0,
   "mandatory_depends_on": null,
   "modified": "2021-12-25 13:09:22.462290",
   "modified_by": "Administrator",
   "module": null,
   "name": "Sales Invoice Item-total_amount",
   "no_copy": 0,
   "non_negative": 0,
   "options": "currency",
   "owner": "Administrator",
   "parent": null,
   "parentfield": null,
   "parenttype": null,
   "permlevel": 0,
   "precision": "",
   "print_hide": 1,
   "print_hide_if_no_value": 0,
   "print_width": null,
   "read_only": 1,
   "read_only_depends_on": null,
   "report_hide": 0,
   "reqd": 0,
   "search_index": 0,
   "sort_options": 0,
   "translatable": 0,
   "unique": 0,
   "width": null
  },
  {
   "_assign": null,
   "_comments": null,
   "_liked_by": null,
   "_user_tags": null,
   "allow_in_quick_entry": 0,
   "allow_on_submit": 0,
   "bold": 0,
   "collapsible": 0,
   "collapsible_depends_on": null,
   "columns": 0,
   "creation": "2023-10-29 08:53:42.100927",
   "default": null,
   "depends_on": null,
   "description": null,
   "docstatus": 0,
   "dt": "Sales Invoice Item",
   "fetch_from": null,
   "fetch_if_empty": 0,
   "fieldname": "delivery_date",
   "fieldtype": "Date",
   "hidden": 0,
   "hide_border": 0,
   "hide_days": 0,
   "hide_seconds": 0,
   "idx": 7,
   "ignore_user_permissions": 0,
   "ignore_xss_filter": 0,
   "in_global_search": 0,
   "in_list_view": 0,
   "in_preview": 0,
   "in_standard_filter": 0,
   "insert_after": "custom_booklet_id",
   "is_system_generated": 0,
   "is_virtual": 0,
   "label": "Delivery Date",
   "length": 0,
   "mandatory_depends_on": null,
   "modified": "2021-12-25 13:09:22.617994",
   "modified_by": "Administrator",
   "module": null,
   "name": "Sales Invoice Item-delivery_date",
   "no_copy": 0,
   "non_negative": 0,
   "options": null,
   "owner": null,
   "parent": null,
   "parentfield": null,
   "parenttype": null,
   "permlevel": 0,
   "precision": "",
   "print_hide": 1,
   "print_hide_if_no_value": 0,
   "print_width": null,
   "read_only": 0,
   "read_only_depends_on": null,
   "report_hide": 0,
   "reqd": 0,
   "search_index": 0,
   "sort_options": 0,
   "translatable": 0,
   "unique": 0,
   "width": null
  },
  {
   "_assign": null,
   "_comments": null,
   "_liked_by": null,
   "_user_tags": null,
   "allow_in_quick_entry": 0,
   "allow_on_submit": 0,
   "bold": 0,
   "collapsible": 0,
   "collapsible_depends_on": null,
   "columns": 0,
   "creation": "2022-11-17 14:43:26.767301",
   "default": null,
   "depends_on": null,
   "description": null,
   "docstatus": 0,
   "dt": "Sales Invoice Item",
   "fetch_from": "item_code.is_zero_rated",
   "fetch_if_empty": 0,
   "fieldname": "is_zero_rated",
   "fieldtype": "Check",
   "hidden": 0,
   "hide_border": 0,
   "hide_days": 0,
   "hide_seconds": 0,
   "idx": 12,
   "ignore_user_permissions": 0,
   "ignore_xss_filter": 0,
   "in_global_search": 0,
   "in_list_view": 0,
   "in_preview": 0,
   "in_standard_filter": 0,
   "insert_after": "total_amount",
   "is_system_generated": 1,
   "is_virtual": 0,
   "label": "Is Zero Rated",
   "length": 0,
   "mandatory_depends_on": null,
   "modified": "2021-12-25 13:09:22.784511",
   "modified_by": "Administrator",
   "module": null,
   "name": "Sales Invoice Item-is_zero_rated",
   "no_copy": 0,
   "non_negative": 0,
   "options": null,
   "owner": "Administrator",
   "parent": null,
   "parentfield": null,
   "parenttype": null,
   "permlevel": 0,
   "precision": "",
   "print_hide": 1,
   "print_hide_if_no_value": 0,
   "print_width": null,
   "read_only": 0,
   "read_only_depends_on": null,
   "report_hide": 0,
   "reqd": 0,
   "search_index": 0,
   "sort_options": 0,
   "translatable": 0,
   "unique": 0,
   "width": null
  },
  {
   "_assign": null,
   "_comments": null,
   "_liked_by": null,
   "_user_tags": null,
   "allow_in_quick_entry": 0,
   "allow_on_submit": 0,
   "bold": 0,
   "collapsible": 0,
   "collapsible_depends_on": null,
   "columns": 0,
   "creation": "2022-11-17 14:43:28.752204",
   "default": null,
   "depends_on": null,
   "description": null,
   "docstatus": 0,
   "dt": "Sales Invoice Item",
   "fetch_from": "item_code.is_exempt",
   "fetch_if_empty": 0,
   "fieldname": "is_exempt",
   "fieldtype": "Check",
   "hidden": 0,
   "hide_border": 0,
   "hide_days": 0,
   "hide_seconds": 0,
   "idx": 13,
   "ignore_user_permissions": 0,
   "ignore_xss_filter": 0,
   "in_global_search": 0,
   "in_list_view": 0,
   "in_preview": 0,
   "in_standard_filter": 0,
   "insert_after": "is_zero_rated",
   "is_system_generated": 1,
   "is_virtual": 0,
   "label": "Is Exempt",
   "length": 0,
   "mandatory_depends_on": null,
   "modified": "2021-12-25 13:09:22.946883",
   "modified_by": "Administrator",
   "module": null,
   "name": "Sales Invoice Item-is_exempt",
   "no_copy": 0,
   "non_negative": 0,
   "options": null,
   "owner": "Administrator",
   "parent": null,
   "parentfield": null,
   "parenttype": null,
   "permlevel": 0,
   "precision": "",
   "print_hide": 1,
   "print_hide_if_no_value": 0,
   "print_width": null,
   "read_only": 0,
   "read_only_depends_on": null,
   "report_hide": 0,
   "reqd": 0,
   "search_index": 0,
   "sort_options": 0,
   "translatable": 0,
   "unique": 0,
   "width": null
  },
  {
   "_assign": null,
   "_comments": null,
   "_liked_by": null,
   "_user_tags": null,
   "allow_in_quick_entry": 0,
   "allow_on_submit": 0,
   "bold": 0,
   "collapsible": 0,
   "collapsible_depends_on": null,
   "columns": 0,
   "creation": "2022-11-17 14:44:42.432570",
   "default": null,
   "depends_on": null,
   "description": null,
   "docstatus": 0,
   "dt": "Sales Invoice Item",
   "fetch_from": null,
   "fetch_if_empty": 0,
   "fieldname": "dimension_department",
   "fieldtype": "Link",
   "hidden": 0,
   "hide_border": 0,
   "hide_days": 0,
   "hide_seconds": 0,
   "idx": 97,
   "ignore_user_permissions": 0,
   "ignore_xss_filter": 0,
   "in_global_search": 0,
   "in_list_view": 1,
   "in_preview": 0,
   "in_standard_filter": 0,
   "insert_after": "accounting_dimensions_section",
   "is_system_generated": 1,
   "is_virtual": 0,
   "label": "Department",
   "length": 0,
   "mandatory_depends_on": null,
   "modified": "2022-01-03 09:16:20.702175",
   "modified_by": "Administrator",
   "module": null,
   "name": "Sales Invoice Item-dimension_department",
   "no_copy": 0,
   "non_negative": 0,
   "options": "Dimension Department",
   "owner": "Administrator",
   "parent": null,
   "parentfield": null,
   "parenttype": null,
   "permlevel": 0,
   "precision": "",
   "print_hide": 0,
   "print_hide_if_no_value": 0,
   "print_width": null,
   "read_only": 0,
   "read_only_depends_on": null,
   "report_hide": 0,
   "reqd": 0,
   "search_index": 0,
   "sort_options": 0,
   "translatable": 0,
   "unique": 0,
   "width": null
  },
  {
   "_assign": null,
   "_comments": null,
   "_liked_by": null,
   "_user_tags": null,
   "allow_in_quick_entry": 0,
   "allow_on_submit": 0,
   "bold": 0,
   "collapsible": 0,
   "collapsible_depends_on": null,
   "columns": 1,
   "creation": "2022-11-17 14:44:42.836946",
   "default": null,
   "depends_on": null,
   "description": null,
   "docstatus": 0,
   "dt": "Sales Invoice Item",
   "fetch_from": null,
   "fetch_if_empty": 0,
   "fieldname": "dimension_branch",
   "fieldtype": "Link",
   "hidden": 0,
   "hide_border": 0,
   "hide_days": 0,
   "hide_seconds": 0,
   "idx": 99,
   "ignore_user_permissions": 0,
   "ignore_xss_filter": 0,
   "in_global_search": 0,
   "in_list_view": 1,
   "in_preview": 0,
   "in_standard_filter": 0,
   "insert_after": "dimension_brand",
   "is_system_generated": 1,
   "is_virtual": 0,
   "label": "Branch",
   "length": 0,
   "mandatory_depends_on": null,
   "modified": "2022-01-03 09:36:58.009337",
   "modified_by": "Administrator",
   "module": null,
   "name": "Sales Invoice Item-dimension_branch",
   "no_copy": 0,
   "non_negative": 0,
   "options": "Dimension Branch",
   "owner": "Administrator",
   "parent": null,
   "parentfield": null,
   "parenttype": null,
   "permlevel": 0,
   "precision": "",
   "print_hide": 0,
   "print_hide_if_no_value": 0,
   "print_width": null,
   "read_only": 0,
   "read_only_depends_on": null,
   "report_hide": 0,
   "reqd": 0,
   "search_index": 0,
   "sort_options": 0,
   "translatable": 0,
   "unique": 0,
   "width": null
  },
  {
   "_assign": null,
   "_comments": null,
   "_liked_by": null,
   "_user_tags": null,
   "allow_in_quick_entry": 0,
   "allow_on_submit": 0,
   "bold": 0,
   "collapsible": 0,
   "collapsible_depends_on": null,
   "columns": 0,
   "creation": "2022-11-17 14:44:42.632214",
   "default": null,
   "depends_on": null,
   "description": null,
   "docstatus": 0,
   "dt": "Sales Invoice Item",
   "fetch_from": null,
   "fetch_if_empty": 0,
   "fieldname": "dimension_brand",
   "fieldtype": "Link",
   "hidden": 0,
   "hide_border": 0,
   "hide_days": 0,
   "hide_seconds": 0,
   "idx": 98,
   "ignore_user_permissions": 0,
   "ignore_xss_filter": 0,
   "in_global_search": 0,
   "in_list_view": 0,
   "in_preview": 0,
   "in_standard_filter": 0,
   "insert_after": "dimension_department",
   "is_system_generated": 1,
   "is_virtual": 0,
   "label": "Brand",
   "length": 0,
   "mandatory_depends_on": null,
   "modified": "2022-01-03 09:38:07.918185",
   "modified_by": "Administrator",
   "module": null,
   "name": "Sales Invoice Item-dimension_brand",
   "no_copy": 0,
   "non_negative": 0,
   "options": "Dimension Brand",
   "owner": "Administrator",
   "parent": null,
   "parentfield": null,
   "parenttype": null,
   "permlevel": 0,
   "precision": "",
   "print_hide": 0,
   "print_hide_if_no_value": 0,
   "print_width": null,
   "read_only": 0,
   "read_only_depends_on": null,
   "report_hide": 0,
   "reqd": 0,
   "search_index": 0,
   "sort_options": 0,
   "translatable": 0,
   "unique": 0,
   "width": null
  },
  {
   "_assign": null,
   "_comments": null,
   "_liked_by": null,
   "_user_tags": null,
   "allow_in_quick_entry": 0,
   "allow_on_submit": 0,
   "bold": 0,
   "collapsible": 0,
   "collapsible_depends_on": null,
   "columns": 0,
   "creation": "2022-11-17 14:44:43.222226",
   "default": null,
   "depends_on": null,
   "description": null,
   "docstatus": 0,
   "dt": "Sales Invoice Item",
   "fetch_from": null,
   "fetch_if_empty": 0,
   "fieldname": "dimension_city",
   "fieldtype": "Link",
   "hidden": 0,
   "hide_border": 0,
   "hide_days": 0,
   "hide_seconds": 0,
   "idx": 102,
   "ignore_user_permissions": 0,
   "ignore_xss_filter": 0,
   "in_global_search": 0,
   "in_list_view": 0,
   "in_preview": 0,
   "in_standard_filter": 0,
   "insert_after": "dimension_col_break",
   "is_system_generated": 1,
   "is_virtual": 0,
   "label": "City",
   "length": 0,
   "mandatory_depends_on": null,
   "modified": "2022-01-03 09:38:22.392214",
   "modified_by": "Administrator",
   "module": null,
   "name": "Sales Invoice Item-dimension_city",
   "no_copy": 0,
   "non_negative": 0,
   "options": "Dimension City",
   "owner": "Administrator",
   "parent": null,
   "parentfield": null,
   "parenttype": null,
   "permlevel": 0,
   "precision": "",
   "print_hide": 0,
   "print_hide_if_no_value": 0,
   "print_width": null,
   "read_only": 0,
   "read_only_depends_on": null,
   "report_hide": 0,
   "reqd": 0,
   "search_index": 0,
   "sort_options": 0,
   "translatable": 0,
   "unique": 0,
   "width": null
  },
  {
   "_assign": null,
   "_comments": null,
   "_liked_by": null,
   "_user_tags": null,
   "allow_in_quick_entry": 0,
   "allow_on_submit": 0,
   "bold": 0,
   "collapsible": 0,
   "collapsible_depends_on": null,
   "columns": 0,
   "creation": "2022-11-17 14:44:41.258344",
   "default": null,
   "depends_on": null,
   "description": null,
   "docstatus": 0,
   "dt": "Sales Invoice Item",
   "fetch_from": null,
   "fetch_if_empty": 0,
   "fieldname": "sales_order_no",
   "fieldtype": "Data",
   "hidden": 0,
   "hide_border": 0,
   "hide_days": 0,
   "hide_seconds": 0,
   "idx": 90,
   "ignore_user_permissions": 0,
   "ignore_xss_filter": 0,
   "in_global_search": 0,
   "in_list_view": 0,
   "in_preview": 0,
   "in_standard_filter": 0,
   "insert_after": "so_detail",
   "is_system_generated": 1,
   "is_virtual": 0,
   "label": "Sales Order No",
   "length": 0,
   "mandatory_depends_on": null,
   "modified": "2022-07-08 14:30:39.213555",
   "modified_by": "Administrator",
   "module": null,
   "name": "Sales Invoice Item-sales_order_no",
   "no_copy": 0,
   "non_negative": 0,
   "options": null,
   "owner": "Administrator",
   "parent": null,
   "parentfield": null,
   "parenttype": null,
   "permlevel": 0,
   "precision": "",
   "print_hide": 0,
   "print_hide_if_no_value": 0,
   "print_width": null,
   "read_only": 0,
   "read_only_depends_on": null,
   "report_hide": 0,
   "reqd": 0,
   "search_index": 0,
   "sort_options": 0,
   "translatable": 1,
   "unique": 0,
   "width": null
  },
  {
   "_assign": null,
   "_comments": null,
   "_liked_by": null,
   "_user_tags": null,
   "allow_in_quick_entry": 0,
   "allow_on_submit": 0,
   "bold": 0,
   "collapsible": 0,
   "collapsible_depends_on": null,
   "columns": 0,
   "creation": "2022-11-17 14:44:46.530641",
   "default": null,
   "depends_on": null,
   "description": null,
   "docstatus": 0,
   "dt": "Sales Invoice Item",
   "fetch_from": null,
   "fetch_if_empty": 0,
   "fieldname": "reference_pos",
   "fieldtype": "Text",
   "hidden": 0,
   "hide_border": 0,
   "hide_days": 0,
   "hide_seconds": 0,
   "idx": 109,
   "ignore_user_permissions": 0,
   "ignore_xss_filter": 0,
   "in_global_search": 0,
   "in_list_view": 0,
   "in_preview": 0,
   "in_standard_filter": 0,
   "insert_after": "is_non_gst",
   "is_system_generated": 1,
   "is_virtual": 0,
   "label": "Reference POS",
   "length": 0,
   "mandatory_depends_on": null,
   "modified": "2022-08-04 13:51:29.230259",
   "modified_by": "Administrator",
   "module": null,
   "name": "Sales Invoice Item-reference_pos",
   "no_copy": 0,
   "non_negative": 0,
   "options": null,
   "owner": "Administrator",
   "parent": null,
   "parentfield": null,
   "parenttype": null,
   "permlevel": 0,
   "precision": "",
   "print_hide": 0,
   "print_hide_if_no_value": 0,
   "print_width": null,
   "read_only": 0,
   "read_only_depends_on": null,
   "report_hide": 0,
   "reqd": 0,
   "search_index": 0,
   "sort_options": 0,
   "translatable": 1,
   "unique": 0,
   "width": null
  },
  {
   "_assign": null,
   "_comments": null,
   "_liked_by": null,
   "_user_tags": null,
   "allow_in_quick_entry": 0,
   "allow_on_submit": 0,
   "bold": 0,
   "collapsible": 0,
   "collapsible_depends_on": null,
   "columns": 0,
   "creation": "2023-10-29 08:50:21.859356",
   "default": null,
   "depends_on": null,
   "description": null,
   "docstatus": 0,
   "dt": "Sales Invoice Item",
   "fetch_from": null,
   "fetch_if_empty": 0,
   "fieldname": "custom_booklet_id",
   "fieldtype": "Link",
   "hidden": 0,
   "hide_border": 0,
   "hide_days": 0,
   "hide_seconds": 0,
   "idx": 6,
   "ignore_user_permissions": 0,
   "ignore_xss_filter": 0,
   "in_global_search": 0,
   "in_list_view": 0,
   "in_preview": 0,
   "in_standard_filter": 0,
   "insert_after": "item_name",
   "is_system_generated": 0,
   "is_virtual": 0,
   "label": "Booklet ID",
   "length": 0,
   "mandatory_depends_on": null,
   "modified": "2023-10-10 12:08:23.346727",
   "modified_by": "Administrator",
   "module": null,
   "name": "Sales Invoice Item-custom_booklet_id",
   "no_copy": 0,
   "non_negative": 0,
   "options": "Booklets",
   "owner": null,
   "parent": null,
   "parentfield": null,
   "parenttype": null,
   "permlevel": 0,
   "precision": "",
   "print_hide": 0,
   "print_hide_if_no_value": 0,
   "print_width": null,
   "read_only": 1,
   "read_only_depends_on": null,
   "report_hide": 0,
   "reqd": 0,
   "search_index": 0,
   "sort_options": 0,
   "translatable": 0,
   "unique": 0,
   "width": null
  },
  {
   "_assign": null,
   "_comments": null,
   "_liked_by": null,
   "_user_tags": null,
   "allow_in_quick_entry": 0,
   "allow_on_submit": 0,
   "bold": 0,
   "collapsible": 0,
   "collapsible_depends_on": null,
   "columns": 0,
   "creation": "2023-11-21 14:28:12.170257",
   "default": null,
   "depends_on": null,
   "description": null,
   "docstatus": 0,
   "dt": "Sales Invoice Item",
   "fetch_from": null,
   "fetch_if_empty": 0,
   "fieldname": "custom_pos_invoice",
   "fieldtype": "Link",
   "hidden": 0,
   "hide_border": 0,
   "hide_days": 0,
   "hide_seconds": 0,
   "idx": 118,
   "ignore_user_permissions": 0,
   "ignore_xss_filter": 0,
   "in_global_search": 0,
   "in_list_view": 0,
   "in_preview": 0,
   "in_standard_filter": 0,
   "insert_after": "reference_pos",
   "is_system_generated": 0,
   "is_virtual": 0,
   "label": "POS INVOICE",
   "length": 0,
   "mandatory_depends_on": null,
   "modified": "2023-11-21 14:28:12.170257",
   "modified_by": "Administrator",
   "module": null,
   "name": "Sales Invoice Item-custom_pos_invoice",
   "no_copy": 0,
   "non_negative": 0,
   "options": "POS Invoice",
   "owner": "Administrator",
   "parent": null,
   "parentfield": null,
   "parenttype": null,
   "permlevel": 0,
   "precision": "",
   "print_hide": 0,
   "print_hide_if_no_value": 0,
   "print_width": null,
   "read_only": 1,
   "read_only_depends_on": null,
   "report_hide": 0,
   "reqd": 0,
   "search_index": 0,
   "sort_options": 0,
   "translatable": 0,
   "unique": 0,
   "width": null
  }
 ],
 "custom_perms": [],
 "doctype": "Sales Invoice Item",
 "links": [],
 "property_setters": [
  {
   "_assign": null,
   "_comments": null,
   "_liked_by": null,
   "_user_tags": null,
   "creation": "2023-11-21 14:28:11.784733",
   "default_value": null,
   "doc_type": "Sales Invoice Item",
   "docstatus": 0,
   "doctype_or_field": "DocType",
   "field_name": null,
   "idx": 0,
   "is_system_generated": 0,
   "modified": "2023-11-21 14:28:11.784733",
   "modified_by": "Administrator",
   "module": null,
   "name": "Sales Invoice Item-main-field_order",
   "owner": "Administrator",
   "parent": null,
   "parentfield": null,
   "parenttype": null,
   "property": "field_order",
   "property_type": "Data",
   "row_name": null,
   "value": "[\"barcode\", \"has_item_scanned\", \"item_code\", \"col_break1\", \"item_name\", \"custom_booklet_id\", \"delivery_date\", \"customer_item_code\", \"description_section\", \"description\", \"tax_code\", \"tax_rate\", \"tax_amount\", \"total_amount\", \"is_zero_rated\", \"is_exempt\", \"item_group\", \"brand\", \"image_section\", \"image\", \"image_view\", \"quantity_and_rate\", \"qty\", \"stock_uom\", \"col_break2\", \"uom\", \"conversion_factor\", \"stock_qty\", \"section_break_17\", \"price_list_rate\", \"base_price_list_rate\", \"discount_and_margin\", \"margin_type\", \"margin_rate_or_amount\", \"rate_with_margin\", \"column_break_19\", \"discount_percentage\", \"discount_amount\", \"base_rate_with_margin\", \"section_break1\", \"rate\", \"amount\", \"item_tax_template\", \"col_break3\", \"base_rate\", \"base_amount\", \"pricing_rules\", \"stock_uom_rate\", \"is_free_item\", \"grant_commission\", \"section_break_21\", \"net_rate\", \"net_amount\", \"column_break_24\", \"base_net_rate\", \"base_net_amount\", \"taxable_value\", \"drop_ship\", \"delivered_by_supplier\", \"accounting\", \"income_account\", \"is_fixed_asset\", \"asset\", \"finance_book\", \"col_break4\", \"expense_account\", \"discount_account\", \"deferred_revenue\", \"deferred_revenue_account\", \"service_stop_date\", \"enable_deferred_revenue\", \"column_break_50\", \"service_start_date\", \"service_end_date\", \"section_break_18\", \"weight_per_unit\", \"total_weight\", \"column_break_21\", \"weight_uom\", \"warehouse_and_reference\", \"warehouse\", \"target_warehouse\", \"quality_inspection\", \"batch_no\", \"incoming_rate\", \"col_break5\", \"allow_zero_valuation_rate\", \"serial_no\", \"item_tax_rate\", \"actual_batch_qty\", \"actual_qty\", \"edit_references\", \"sales_order\", \"so_detail\", \"sales_order_no\", \"sales_invoice_item\", \"column_break_74\", \"delivery_note\", \"dn_detail\", \"delivered_qty\", \"internal_transfer_section\", \"purchase_order\", \"column_break_92\", \"purchase_order_item\", \"accounting_dimensions_section\", \"dimension_department\", \"dimension_brand\", \"dimension_branch\", \"cost_center\", \"dimension_col_break\", \"dimension_city\", \"project\", \"section_break_54\", \"page_break\", \"gst_hsn_code\", \"is_nil_exempt\", \"is_non_gst\", \"reference_pos\", null]"
  },
  {
   "_assign": null,
   "_comments": null,
   "_liked_by": null,
   "_user_tags": null,
   "creation": "2023-10-29 08:34:57.091735",
   "default_value": null,
   "doc_type": "Sales Invoice Item",
   "docstatus": 0,
   "doctype_or_field": "DocField",
   "field_name": "target_warehouse",
   "idx": 0,
   "is_system_generated": 0,
   "modified": "2022-01-05 09:40:43.974724",
   "modified_by": "Administrator",
   "module": null,
   "name": "Sales Invoice Item-target_warehouse-hidden",
   "owner": null,
   "parent": null,
   "parentfield": null,
   "parenttype": null,
   "property": "hidden",
   "property_type": "Check",
   "row_name": null,
   "value": "1"
  },
  {
   "_assign": null,
   "_comments": null,
   "_liked_by": null,
   "_user_tags": null,
   "creation": "2023-10-29 08:34:56.769120",
   "default_value": null,
   "doc_type": "Sales Invoice Item",
   "docstatus": 0,
   "doctype_or_field": "DocField",
   "field_name": "barcode",
   "idx": 0,
   "is_system_generated": 0,
   "modified": "2022-01-05 09:40:43.487835",
   "modified_by": "Administrator",
   "module": null,
   "name": "Sales Invoice Item-barcode-hidden",
   "owner": null,
   "parent": null,
   "parentfield": null,
   "parenttype": null,
   "property": "hidden",
   "property_type": "Check",
   "row_name": null,
   "value": "0"
  },
  {
   "_assign": null,
   "_comments": null,
   "_liked_by": null,
   "_user_tags": null,
   "creation": "2023-10-29 08:34:56.611064",
   "default_value": null,
   "doc_type": "Sales Invoice Item",
   "docstatus": 0,
   "doctype_or_field": "DocField",
   "field_name": "page_break",
   "idx": 0,
   "is_system_generated": 0,
   "modified": "2022-01-03 09:44:13.842878",
   "modified_by": "Administrator",
   "module": null,
   "name": "Sales Invoice Item-page_break-in_list_view",
   "owner": null,
   "parent": null,
   "parentfield": null,
   "parenttype": null,
   "property": "in_list_view",
   "property_type": "Check",
   "row_name": null,
   "value": "1"
  },
  {
   "_assign": null,
   "_comments": null,
   "_liked_by": null,
   "_user_tags": null,
   "creation": "2023-10-29 08:34:56.449892",
   "default_value": null,
   "doc_type": "Sales Invoice Item",
   "docstatus": 0,
   "doctype_or_field": "DocField",
   "field_name": "project",
   "idx": 0,
   "is_system_generated": 0,
   "modified": "2022-01-03 09:44:13.752360",
   "modified_by": "Administrator",
   "module": null,
   "name": "Sales Invoice Item-project-in_list_view",
   "owner": null,
   "parent": null,
   "parentfield": null,
   "parenttype": null,
   "property": "in_list_view",
   "property_type": "Check",
   "row_name": null,
   "value": "1"
  },
  {
   "_assign": null,
   "_comments": null,
   "_liked_by": null,
   "_user_tags": null,
   "creation": "2023-10-29 08:34:53.439510",
   "default_value": null,
   "doc_type": "Sales Invoice Item",
   "docstatus": 0,
   "doctype_or_field": "DocField",
   "field_name": "item_code",
   "idx": 0,
   "is_system_generated": 0,
   "modified": "2020-05-18 09:20:57.030757",
   "modified_by": "Administrator",
   "module": null,
   "name": "Sales Invoice Item-item_code-width",
   "owner": null,
   "parent": null,
   "parentfield": null,
   "parenttype": null,
   "property": "width",
   "property_type": "Data",
   "row_name": null,
   "value": "13%"
  },
  {
   "_assign": null,
   "_comments": null,
   "_liked_by": null,
   "_user_tags": null,
   "creation": "2023-10-29 08:34:53.276346",
   "default_value": null,
   "doc_type": "Sales Invoice Item",
   "docstatus": 0,
   "doctype_or_field": "DocField",
   "field_name": "item_tax_template",
   "idx": 0,
   "is_system_generated": 0,
   "modified": "2020-05-18 09:07:00.257718",
   "modified_by": "Administrator",
   "module": null,
   "name": "Sales Invoice Item-item_tax_template-columns",
   "owner": null,
   "parent": null,
   "parentfield": null,
   "parenttype": null,
   "property": "columns",
   "property_type": "Int",
   "row_name": null,
   "value": "1"
  },
  {
   "_assign": null,
   "_comments": null,
   "_liked_by": null,
   "_user_tags": null,
   "creation": "2023-10-29 08:34:53.115602",
   "default_value": null,
   "doc_type": "Sales Invoice Item",
   "docstatus": 0,
   "doctype_or_field": "DocField",
   "field_name": "amount",
   "idx": 0,
   "is_system_generated": 0,
   "modified": "2020-05-18 09:06:19.002663",
   "modified_by": "Administrator",
   "module": null,
   "name": "Sales Invoice Item-amount-columns",
   "owner": null,
   "parent": null,
   "parentfield": null,
   "parenttype": null,
   "property": "columns",
   "property_type": "Int",
   "row_name": null,
   "value": "1"
  },
  {
   "_assign": null,
   "_comments": null,
   "_liked_by": null,
   "_user_tags": null,
   "creation": "2023-10-29 08:34:52.949090",
   "default_value": null,
   "doc_type": "Sales Invoice Item",
   "docstatus": 0,
   "doctype_or_field": "DocField",
   "field_name": "item_tax_template",
   "idx": 0,
   "is_system_generated": 0,
   "modified": "2020-05-18 09:02:51.019275",
   "modified_by": "Administrator",
   "module": null,
   "name": "Sales Invoice Item-item_tax_template-in_list_view",
   "owner": null,
   "parent": null,
   "parentfield": null,
   "parenttype": null,
   "property": "in_list_view",
   "property_type": "Check",
   "row_name": null,
   "value": "1"
  },
  {
   "_assign": null,
   "_comments": null,
   "_liked_by": null,
   "_user_tags": null,
   "creation": "2023-10-29 08:34:54.484131",
   "default_value": null,
   "doc_type": "Sales Invoice Item",
   "docstatus": 0,
   "doctype_or_field": "DocField",
   "field_name": "item_code",
   "idx": 0,
   "is_system_generated": 0,
   "modified": "2020-04-20 10:30:09.905722",
   "modified_by": "Administrator",
   "module": null,
   "name": "Sales Invoice Item-item_code-columns",
   "owner": null,
   "parent": null,
   "parentfield": null,
   "parenttype": null,
   "property": "columns",
   "property_type": "Int",
   "row_name": null,
   "value": "3"
  },
  {
   "_assign": null,
   "_comments": null,
   "_liked_by": null,
   "_user_tags": null,
   "creation": "2023-10-29 08:34:54.313073",
   "default_value": null,
   "doc_type": "Sales Invoice Item",
   "docstatus": 0,
   "doctype_or_field": "DocField",
   "field_name": "serial_no",
   "idx": 0,
   "is_system_generated": 0,
   "modified": "2020-04-20 09:56:48.921871",
   "modified_by": "Administrator",
   "module": null,
   "name": "Sales Invoice Item-serial_no-in_list_view",
   "owner": null,
   "parent": null,
   "parentfield": null,
   "parenttype": null,
   "property": "in_list_view",
   "property_type": "Check",
   "row_name": null,
   "value": "0"
  },
  {
   "_assign": null,
   "_comments": null,
   "_liked_by": null,
   "_user_tags": null,
   "creation": "2023-10-29 08:34:54.132852",
   "default_value": null,
   "doc_type": "Sales Invoice Item",
   "docstatus": 0,
   "doctype_or_field": "DocField",
   "field_name": "batch_no",
   "idx": 0,
   "is_system_generated": 0,
   "modified": "2020-04-20 09:55:14.196463",
   "modified_by": "Administrator",
   "module": null,
   "name": "Sales Invoice Item-batch_no-in_list_view",
   "owner": null,
   "parent": null,
   "parentfield": null,
   "parenttype": null,
   "property": "in_list_view",
   "property_type": "Check",
   "row_name": null,
   "value": "0"
  },
  {
   "_assign": null,
   "_comments": null,
   "_liked_by": null,
   "_user_tags": null,
   "creation": "2023-10-29 08:34:53.954187",
   "default_value": null,
   "doc_type": "Sales Invoice Item",
   "docstatus": 0,
   "doctype_or_field": "DocField",
   "field_name": "warehouse",
   "idx": 0,
   "is_system_generated": 0,
   "modified": "2020-04-20 09:55:14.064066",
   "modified_by": "Administrator",
   "module": null,
   "name": "Sales Invoice Item-warehouse-in_list_view",
   "owner": null,
   "parent": null,
   "parentfield": null,
   "parenttype": null,
   "property": "in_list_view",
   "property_type": "Check",
   "row_name": null,
   "value": "0"
  },
  {
   "_assign": null,
   "_comments": null,
   "_liked_by": null,
   "_user_tags": null,
   "creation": "2023-10-29 08:34:53.770414",
   "default_value": null,
   "doc_type": "Sales Invoice Item",
   "docstatus": 0,
   "doctype_or_field": "DocField",
   "field_name": "rate",
   "idx": 0,
   "is_system_generated": 0,
   "modified": "2020-04-20 09:52:59.387818",
   "modified_by": "Administrator",
   "module": null,
   "name": "Sales Invoice Item-rate-columns",
   "owner": null,
   "parent": null,
   "parentfield": null,
   "parenttype": null,
   "property": "columns",
   "property_type": "Int",
   "row_name": null,
   "value": "1"
  },
  {
   "_assign": null,
   "_comments": null,
   "_liked_by": null,
   "_user_tags": null,
   "creation": "2023-10-29 08:34:53.607345",
   "default_value": null,
   "doc_type": "Sales Invoice Item",
   "docstatus": 0,
   "doctype_or_field": "DocField",
   "field_name": "qty",
   "idx": 0,
   "is_system_generated": 0,
   "modified": "2020-04-20 09:52:59.302929",
   "modified_by": "Administrator",
   "module": null,
   "name": "Sales Invoice Item-qty-columns",
   "owner": null,
   "parent": null,
   "parentfield": null,
   "parenttype": null,
   "property": "columns",
   "property_type": "Int",
   "row_name": null,
   "value": "1"
  }
 ],
 "sync_on_migrate": 1
}